MYLAVLIBFORPYTHON/__init__.py
MYLAVLIBFORPYTHON/module1.py
MYLAVLIBFORPYTHON/module2.py
MYLABLIBFORPYTHON-0.1.0.dist-info/METADATA
MYLABLIBFORPYTHON-0.1.0.dist-info/WHEEL
MYLABLIBFORPYTHON-0.1.0.dist-info/top_level.txt
MYLABLIBFORPYTHON-0.1.0.dist-info/RECORD
